{
  "id": "mem-prop-5x6",
  "name": "mem proportional 5x6",
  "cel_width": 5,
  "cel_height": 6,
  "leading": 1,
  "kerning": {
    "##": -1,
    ",'": 0,
    ",\"": 0,
    ",`": 0,
    ".'": 0,
    ".\"": 0,
    ".`": 0,
    "//": -2,
    "::": 0,
    ";:": 0,
    ";;": 0,
    "\\\\": -2,
    "_\"": 0,
    "_'": 0,
    "_`": 0,
    "_t": 0,
    "-'": 0,
    "-\"": 0,
    "-`": 0,
    "--": 0,
    "'s": 0,
    "'d": 0,
    "PS": 0,
    "T,": 0,
    "ZY": 0,
    "d;": 0,
    "n'": 0,
    "qr": 0,
    "qu": 0,
    "rj": -1,
    "rs": 0,
    "s.": 0,
    "sj": 0,
    "ss": 0,
    "ts": 0,
    "ys": 0,
    "zz": 0
  },
  "default_kerning": 1,
  "whitespace_kerning": 0,
  "end_of_line_kerning": 0,
  "letter_width": {
    "\u0001": 5,
    "\u0002": 5,
    "\u0003": 5,
    "\u0004": 5,
    "\u0005": 5,
    "\u0006": 5,
    "\u0009": 5,
    "\n": 0,
    "\u000d": 5,
    "\u000e": 5,
    "\u000f": 5,
    "\u0014": 4,
    "\u0016": 5,
    "\u001a": 5,
    "\u001b": 5,
    "\u001d": 5,
    "\u001e": 5,
    "\u001f": 5,
    "!": 1,
    "#": 5,
    "%": 5,
    "&": 4,
    "'": 1,
    "(": 2,
    ")": 2,
    ",": 2,
    ".": 1,
    "/": 5,
    ":": 1,
    ";": 2,
    "?": 4,
    "@": 5,
    "M": 5,
    "W": 5,
    "[": 2,
    "\\": 5,
    "]": 2,
    "`": 2,
    "i": 1,
    "l": 1,
    "m": 5,
    "q": 4,
    "w": 5,
    "|": 1,
    "\u007f": 5
  },
  "default_letter_width": 3
}
